ovos_lang_detector_fasttext_plugin/__init__.py
ovos_lang_detector_fasttext_plugin/version.py
ovos_lang_detector_fasttext_plugin-0.1.1.dist-info/LICENSE
ovos_lang_detector_fasttext_plugin-0.1.1.dist-info/METADATA
ovos_lang_detector_fasttext_plugin-0.1.1.dist-info/WHEEL
ovos_lang_detector_fasttext_plugin-0.1.1.dist-info/entry_points.txt
ovos_lang_detector_fasttext_plugin-0.1.1.dist-info/top_level.txt
ovos_lang_detector_fasttext_plugin-0.1.1.dist-info/RECORD
