Metadata-Version: 2.1
Name: ovos-lang-detector-fasttext-plugin
Version: 0.1.1
Summary: average plugin classifications for language detection
Home-page: https://github.com/OpenVoiceOS/ovos-lang-detector-fasttext-plugin
Author: JarbasAI
Author-email: jarbasai@mailfence.com
License: apache-2
License-File: LICENSE
Requires-Dist: fasttext
Requires-Dist: huggingface-hub
Requires-Dist: langcodes
Requires-Dist: ovos-plugin-manager<2.0.0,>=1.0.0
